perf_baseline/__init__.py
perf_baseline/baseline.py
perf_baseline-0.1.0.dist-info/LICENSE
perf_baseline-0.1.0.dist-info/METADATA
perf_baseline-0.1.0.dist-info/WHEEL
perf_baseline-0.1.0.dist-info/top_level.txt
perf_baseline-0.1.0.dist-info/RECORD
