Metadata-Version: 2.1
Name: perf-baseline
Version: 0.1.0
Summary: The perf_baseline is a performance regression detection tool for Python projects.
Home-page: https://github.com/rayluo/perf_baseline
Author: Ray Luo
Author-email: rayluo.mba@gmail.com
License: MIT
Project-URL: Changelog, https://github.com/rayluo/perf_baseline/releases
Keywords: performance,timeit,baseline,regression,detection
Classifier: Development Status :: 4 - Beta
Classifier: License :: OSI Approved :: MIT License
Classifier: Operating System :: OS Independent
Classifier: Programming Language :: Python
Classifier: Programming Language :: Python :: 3
Classifier: Programming Language :: Python :: 3.7
Classifier: Programming Language :: Python :: 3.8
Classifier: Programming Language :: Python :: 3.9
Classifier: Programming Language :: Python :: 3.10
Classifier: Programming Language :: Python :: 3.11
License-File: LICENSE
